busm/__init__.py
busm/conf/busm.yaml
busm/conf/logging.yaml
busm-0.9.5.dist-info/LICENSE
busm-0.9.5.dist-info/METADATA
busm-0.9.5.dist-info/WHEEL
busm-0.9.5.dist-info/top_level.txt
busm-0.9.5.dist-info/RECORD
