Metadata-Version: 2.1
Name: busm
Version: 0.9.5
Summary: Help you get stdout of function execution through Email, Telegram and Line Notify.
Home-page: https://github.com/virus-warnning/busm
Author: Raymond Wu
License: MIT
Platform: UNKNOWN
Requires-Python: >=3.5
Requires-Dist: requests
Requires-Dist: PyYAML
